pyconversation/__init__.py
pyconversation/loggers/__init__.py
pyconversation/loggers/base.py
pyconversation/loggers/dict_logger.py
pyconversation/loggers/json_file_logger.py
pyconversation/messages/__init__.py
pyconversation/messages/ask.py
pyconversation/messages/base.py
pyconversation/messages/group.py
pyconversation/messages/list_ask.py
pyconversation/messages/switch.py
pyconversation/messages/terminate_group.py
pyconversation/messages/text.py
pyconversation/messages/transfer.py
pyconversation/sender/__init__.py
pyconversation/sender/sender.py
pyconversation/util_types/__init__.py
pyconversation/util_types/message_transfer_generator.py
pyconversation-1.0.7.dist-info/LICENSE
pyconversation-1.0.7.dist-info/METADATA
pyconversation-1.0.7.dist-info/WHEEL
pyconversation-1.0.7.dist-info/top_level.txt
pyconversation-1.0.7.dist-info/RECORD
