Metadata-Version: 2.1
Name: pyconversation
Version: 1.0.7
Summary: Zero-dependency library for chat-bot creators with deadlines. It allows you to describe a conversation, talk with user according to your schema and restore it, if something went wrong.
Home-page: https://github.com/R-Mielamud/py-conversation.git
Author: Roman Melamud
License: MIT
Project-URL: Bugs, https://github.com/R-Mielamud/py-conversation/issues
Project-URL: Homepage, https://github.com/R-Mielamud/py-conversation#readme
Platform: UNKNOWN
Classifier: Programming Language :: Python :: 3
Classifier: License :: OSI Approved :: MIT License
Classifier: Operating System :: OS Independent
Requires-Python: >=3.6
License-File: LICENSE
